bfcl/__init__.py
bfcl/__main__.py
bfcl/_apply_function_credential_config.py
bfcl/_llm_response_generation.py
bfcl/constant.py
bfcl/utils.py
bfcl/custom_datasets/__init__.py
bfcl/custom_datasets/scripts/__init__.py
bfcl/custom_datasets/scripts/process_custom_dataset_for_bfcl.py
bfcl/custom_datasets/utils/__init__.py
bfcl/custom_datasets/utils/custom_data_model.py
bfcl/custom_datasets/utils/process_custom_data.py
bfcl/data/BFCL_v3_chatable.json
bfcl/data/BFCL_v3_exec_multiple.json
bfcl/data/BFCL_v3_exec_parallel.json
bfcl/data/BFCL_v3_exec_parallel_multiple.json
bfcl/data/BFCL_v3_exec_simple.json
bfcl/data/BFCL_v3_irrelevance.json
bfcl/data/BFCL_v3_java.json
bfcl/data/BFCL_v3_javascript.json
bfcl/data/BFCL_v3_live_irrelevance.json
bfcl/data/BFCL_v3_live_multiple.json
bfcl/data/BFCL_v3_live_parallel.json
bfcl/data/BFCL_v3_live_parallel_multiple.json
bfcl/data/BFCL_v3_live_relevance.json
bfcl/data/BFCL_v3_live_simple.json
bfcl/data/BFCL_v3_multi_turn_base.json
bfcl/data/BFCL_v3_multi_turn_composite.json
bfcl/data/BFCL_v3_multi_turn_long_context.json
bfcl/data/BFCL_v3_multi_turn_miss_func.json
bfcl/data/BFCL_v3_multi_turn_miss_param.json
bfcl/data/BFCL_v3_multiple.json
bfcl/data/BFCL_v3_parallel.json
bfcl/data/BFCL_v3_parallel_multiple.json
bfcl/data/BFCL_v3_rest.json
bfcl/data/BFCL_v3_simple.json
bfcl/data/BFCL_v3_sql.json
bfcl/data/README.md
bfcl/data/multi_turn_func_doc/gorilla_file_system.json
bfcl/data/multi_turn_func_doc/math_api.json
bfcl/data/multi_turn_func_doc/message_api.json
bfcl/data/multi_turn_func_doc/posting_api.json
bfcl/data/multi_turn_func_doc/ticket_api.json
bfcl/data/multi_turn_func_doc/trading_bot.json
bfcl/data/multi_turn_func_doc/travel_booking.json
bfcl/data/multi_turn_func_doc/vehicle_control.json
bfcl/data/possible_answer/BFCL_v3_java.json
bfcl/data/possible_answer/BFCL_v3_javascript.json
bfcl/data/possible_answer/BFCL_v3_live_multiple.json
bfcl/data/possible_answer/BFCL_v3_live_parallel.json
nvidia_bfcl-25.11.dist-info/METADATA
nvidia_bfcl-25.11.dist-info/WHEEL
nvidia_bfcl-25.11.dist-info/entry_points.txt
nvidia_bfcl-25.11.dist-info/top_level.txt
nvidia_bfcl-25.11.dist-info/RECORD
