Metadata-Version: 2.4
Name: nvidia_bfcl
Version: 25.11
Summary: Berkeley Function Calling Leaderboard (BFCL) - packaged by NVIDIA
License: Apache 2.0
Project-URL: Repository, https://github.com/ShishirPatil/gorilla/tree/main/berkeley-function-call-leaderboard
Classifier: Development Status :: 5 - Production/Stable
Classifier: Programming Language :: Python :: 3
Classifier: License :: OSI Approved :: Apache Software License
Classifier: Operating System :: OS Independent
Requires-Python: >=3.10
Requires-Dist: requests
Requires-Dist: tqdm
Requires-Dist: numpy==1.26.4
Requires-Dist: pandas
Requires-Dist: huggingface_hub
Requires-Dist: pydantic>=2.8.2
Requires-Dist: python-dotenv>=1.0.1
Requires-Dist: tree_sitter==0.21.3
Requires-Dist: tree-sitter-java==0.21.0
Requires-Dist: tree-sitter-javascript==0.21.4
Requires-Dist: openai>=1.61.0
Requires-Dist: typer>=0.12.5
Requires-Dist: tabulate>=0.9.0
Requires-Dist: datamodel-code-generator==0.25.7
Requires-Dist: mpmath==1.3.0
Requires-Dist: tenacity==9.0.0
Requires-Dist: writer-sdk>=1.2.0
Requires-Dist: overrides
Requires-Dist: nemo-evaluator
Provides-Extra: oss-eval-vllm
Requires-Dist: vllm==0.6.3; extra == "oss-eval-vllm"
Provides-Extra: oss-eval-sglang
Requires-Dist: sglang[all]; extra == "oss-eval-sglang"
Provides-Extra: wandb
Requires-Dist: wandb==0.18.5; extra == "wandb"
